<?xml version="1.0" encoding="ISO-8859-1"?>
<tv generator-info-name="Revista Eletronica - Unidade Lorenz Ltda" generator-info-url="http://www.revistaeletronica.com.br">
<channel id="XTR">
<display-name lang="pt">Xtreme TV - Básica IPTV</display-name>
<icon src="xtr.gif" />
</channel>
<programme start="20150605000000 -0300" stop="20150605040000 -0300" channel="XTR" program_id="0000217661" event_id="00000000000097958645" series_key="">
<title lang="pt">Novidades na sua Locadora Virtual</title>
<desc>Assista na hora que quiser e quantas vezes desejar! Para utilizar a sua Locadora Virtual, basta acessar o botão "Menu" no seu controle remoto e utilizar as teclas de navegação para selecionar a categoria desejada.</desc>
<category lang="pt">Variedades</category>
<category lang="pt">Diversos</category>
<image>
<image_name position="1">0000217661.jpg</image_name>
<image_broadcast>0000217661</image_broadcast>
<image_copyright>Image supplied by Broadcasters</image_copyright>
</image>
<video>
<colour>yes</colour>
</video>
<rating system="Advisory">
<value>Programa livre para todas as idades</value>
</rating>
</programme>
<programme start="20150605040000 -0300" stop="20150605080000 -0300" channel="XTR" program_id="0000217661" event_id="00000000000097958646" series_key="">
<title lang="pt">Novidades na sua Locadora Virtual</title>
<desc>Assista na hora que quiser e quantas vezes desejar! Para utilizar a sua Locadora Virtual, basta acessar o botão "Menu" no seu controle remoto e utilizar as teclas de navegação para selecionar a categoria desejada.</desc>
<category lang="pt">Variedades</category>
<category lang="pt">Diversos</category>
<image>
<image_name position="1">0000217661.jpg</image_name>
<image_broadcast>0000217661</image_broadcast>
<image_copyright>Image supplied by Broadcasters</image_copyright>
</image>
<video>
<colour>yes</colour>
</video>
<rating system="Advisory">
<value>Programa livre para todas as idades</value>
</rating>
</programme>
<programme start="20150605080000 -0300" stop="20150605120000 -0300" channel="XTR" program_id="0000217661" event_id="00000000000097958647" series_key="">
<title lang="pt">Novidades na sua Locadora Virtual</title>
<desc>Assista na hora que quiser e quantas vezes desejar! Para utilizar a sua Locadora Virtual, basta acessar o botão "Menu" no seu controle remoto e utilizar as teclas de navegação para selecionar a categoria desejada.</desc>
<category lang="pt">Variedades</category>
<category lang="pt">Diversos</category>
<image>
<image_name position="1">0000217661.jpg</image_name>
<image_broadcast>0000217661</image_broadcast>
<image_copyright>Image supplied by Broadcasters</image_copyright>
</image>
<video>
<colour>yes</colour>
</video>
<rating system="Advisory">
<value>Programa livre para todas as idades</value>
</rating>
</programme>
<programme start="20150605120000 -0300" stop="20150605160000 -0300" channel="XTR" program_id="0000217661" event_id="00000000000097958648" series_key="">
<title lang="pt">Novidades na sua Locadora Virtual</title>
<desc>Assista na hora que quiser e quantas vezes desejar! Para utilizar a sua Locadora Virtual, basta acessar o botão "Menu" no seu controle remoto e utilizar as teclas de navegação para selecionar a categoria desejada.</desc>
<category lang="pt">Variedades</category>
<category lang="pt">Diversos</category>
<image>
<image_name position="1">0000217661.jpg</image_name>
<image_broadcast>0000217661</image_broadcast>
<image_copyright>Image supplied by Broadcasters</image_copyright>
</image>
<video>
<colour>yes</colour>
</video>
<rating system="Advisory">
<value>Programa livre para todas as idades</value>
</rating>
</programme>
<programme start="20150605160000 -0300" stop="20150605200000 -0300" channel="XTR" program_id="0000217661" event_id="00000000000097958649" series_key="">
<title lang="pt">Novidades na sua Locadora Virtual</title>
<desc>Assista na hora que quiser e quantas vezes desejar! Para utilizar a sua Locadora Virtual, basta acessar o botão "Menu" no seu controle remoto e utilizar as teclas de navegação para selecionar a categoria desejada.</desc>
<category lang="pt">Variedades</category>
<category lang="pt">Diversos</category>
<image>
<image_name position="1">0000217661.jpg</image_name>
<image_broadcast>0000217661</image_broadcast>
<image_copyright>Image supplied by Broadcasters</image_copyright>
</image>
<video>
<colour>yes</colour>
</video>
<rating system="Advisory">
<value>Programa livre para todas as idades</value>
</rating>
</programme>
<programme start="20150605200000 -0300" stop="20150606000000 -0300" channel="XTR" program_id="0000217661" event_id="00000000000097958650" series_key="">
<title lang="pt">Novidades na sua Locadora Virtual</title>
<desc>Assista na hora que quiser e quantas vezes desejar! Para utilizar a sua Locadora Virtual, basta acessar o botão "Menu" no seu controle remoto e utilizar as teclas de navegação para selecionar a categoria desejada.</desc>
<category lang="pt">Variedades</category>
<category lang="pt">Diversos</category>
<image>
<image_name position="1">0000217661.jpg</image_name>
<image_broadcast>0000217661</image_broadcast>
<image_copyright>Image supplied by Broadcasters</image_copyright>
</image>
<video>
<colour>yes</colour>
</video>
<rating system="Advisory">
<value>Programa livre para todas as idades</value>
</rating>
</programme>
<programme start="20150606000000 -0300" stop="20150606040000 -0300" channel="XTR" program_id="0000217661" event_id="00000000000097958651" series_key="">
<title lang="pt">Novidades na sua Locadora Virtual</title>
<desc>Assista na hora que quiser e quantas vezes desejar! Para utilizar a sua Locadora Virtual, basta acessar o botão "Menu" no seu controle remoto e utilizar as teclas de navegação para selecionar a categoria desejada.</desc>
<category lang="pt">Variedades</category>
<category lang="pt">Diversos</category>
<image>
<image_name position="1">0000217661.jpg</image_name>
<image_broadcast>0000217661</image_broadcast>
<image_copyright>Image supplied by Broadcasters</image_copyright>
</image>
<video>
<colour>yes</colour>
</video>
<rating system="Advisory">
<value>Programa livre para todas as idades</value>
</rating>
</programme>
<programme start="20150606040000 -0300" stop="20150606080000 -0300" channel="XTR" program_id="0000217661" event_id="00000000000097958652" series_key="">
<title lang="pt">Novidades na sua Locadora Virtual</title>
<desc>Assista na hora que quiser e quantas vezes desejar! Para utilizar a sua Locadora Virtual, basta acessar o botão "Menu" no seu controle remoto e utilizar as teclas de navegação para selecionar a categoria desejada.</desc>
<category lang="pt">Variedades</category>
<category lang="pt">Diversos</category>
<image>
<image_name position="1">0000217661.jpg</image_name>
<image_broadcast>0000217661</image_broadcast>
<image_copyright>Image supplied by Broadcasters</image_copyright>
</image>
<video>
<colour>yes</colour>
</video>
<rating system="Advisory">
<value>Programa livre para todas as idades</value>
</rating>
</programme>
<programme start="20150606080000 -0300" stop="20150606120000 -0300" channel="XTR" program_id="0000217661" event_id="00000000000097958653" series_key="">
<title lang="pt">Novidades na sua Locadora Virtual</title>
<desc>Assista na hora que quiser e quantas vezes desejar! Para utilizar a sua Locadora Virtual, basta acessar o botão "Menu" no seu controle remoto e utilizar as teclas de navegação para selecionar a categoria desejada.</desc>
<category lang="pt">Variedades</category>
<category lang="pt">Diversos</category>
<image>
<image_name position="1">0000217661.jpg</image_name>
<image_broadcast>0000217661</image_broadcast>
<image_copyright>Image supplied by Broadcasters</image_copyright>
</image>
<video>
<colour>yes</colour>
</video>
<rating system="Advisory">
<value>Programa livre para todas as idades</value>
</rating>
</programme>
<programme start="20150606120000 -0300" stop="20150606160000 -0300" channel="XTR" program_id="0000217661" event_id="00000000000097958654" series_key="">
<title lang="pt">Novidades na sua Locadora Virtual</title>
<desc>Assista na hora que quiser e quantas vezes desejar! Para utilizar a sua Locadora Virtual, basta acessar o botão "Menu" no seu controle remoto e utilizar as teclas de navegação para selecionar a categoria desejada.</desc>
<category lang="pt">Variedades</category>
<category lang="pt">Diversos</category>
<image>
<image_name position="1">0000217661.jpg</image_name>
<image_broadcast>0000217661</image_broadcast>
<image_copyright>Image supplied by Broadcasters</image_copyright>
</image>
<video>
<colour>yes</colour>
</video>
<rating system="Advisory">
<value>Programa livre para todas as idades</value>
</rating>
</programme>
<programme start="20150606160000 -0300" stop="20150606200000 -0300" channel="XTR" program_id="0000217661" event_id="00000000000097958655" series_key="">
<title lang="pt">Novidades na sua Locadora Virtual</title>
<desc>Assista na hora que quiser e quantas vezes desejar! Para utilizar a sua Locadora Virtual, basta acessar o botão "Menu" no seu controle remoto e utilizar as teclas de navegação para selecionar a categoria desejada.</desc>
<category lang="pt">Variedades</category>
<category lang="pt">Diversos</category>
<image>
<image_name position="1">0000217661.jpg</image_name>
<image_broadcast>0000217661</image_broadcast>
<image_copyright>Image supplied by Broadcasters</image_copyright>
</image>
<video>
<colour>yes</colour>
</video>
<rating system="Advisory">
<value>Programa livre para todas as idades</value>
</rating>
</programme>
<programme start="20150606200000 -0300" stop="20150607000000 -0300" channel="XTR" program_id="0000217661" event_id="00000000000097958656" series_key="">
<title lang="pt">Novidades na sua Locadora Virtual</title>
<desc>Assista na hora que quiser e quantas vezes desejar! Para utilizar a sua Locadora Virtual, basta acessar o botão "Menu" no seu controle remoto e utilizar as teclas de navegação para selecionar a categoria desejada.</desc>
<category lang="pt">Variedades</category>
<category lang="pt">Diversos</category>
<image>
<image_name position="1">0000217661.jpg</image_name>
<image_broadcast>0000217661</image_broadcast>
<image_copyright>Image supplied by Broadcasters</image_copyright>
</image>
<video>
<colour>yes</colour>
</video>
<rating system="Advisory">
<value>Programa livre para todas as idades</value>
</rating>
</programme>
<programme start="20150607000000 -0300" stop="20150607040000 -0300" channel="XTR" program_id="0000217661" event_id="00000000000097958657" series_key="">
<title lang="pt">Novidades na sua Locadora Virtual</title>
<desc>Assista na hora que quiser e quantas vezes desejar! Para utilizar a sua Locadora Virtual, basta acessar o botão "Menu" no seu controle remoto e utilizar as teclas de navegação para selecionar a categoria desejada.</desc>
<category lang="pt">Variedades</category>
<category lang="pt">Diversos</category>
<image>
<image_name position="1">0000217661.jpg</image_name>
<image_broadcast>0000217661</image_broadcast>
<image_copyright>Image supplied by Broadcasters</image_copyright>
</image>
<video>
<colour>yes</colour>
</video>
<rating system="Advisory">
<value>Programa livre para todas as idades</value>
</rating>
</programme>
<programme start="20150607040000 -0300" stop="20150607080000 -0300" channel="XTR" program_id="0000217661" event_id="00000000000097958658" series_key="">
<title lang="pt">Novidades na sua Locadora Virtual</title>
<desc>Assista na hora que quiser e quantas vezes desejar! Para utilizar a sua Locadora Virtual, basta acessar o botão "Menu" no seu controle remoto e utilizar as teclas de navegação para selecionar a categoria desejada.</desc>
<category lang="pt">Variedades</category>
<category lang="pt">Diversos</category>
<image>
<image_name position="1">0000217661.jpg</image_name>
<image_broadcast>0000217661</image_broadcast>
<image_copyright>Image supplied by Broadcasters</image_copyright>
</image>
<video>
<colour>yes</colour>
</video>
<rating system="Advisory">
<value>Programa livre para todas as idades</value>
</rating>
</programme>
<programme start="20150607080000 -0300" stop="20150607120000 -0300" channel="XTR" program_id="0000217661" event_id="00000000000097958659" series_key="">
<title lang="pt">Novidades na sua Locadora Virtual</title>
<desc>Assista na hora que quiser e quantas vezes desejar! Para utilizar a sua Locadora Virtual, basta acessar o botão "Menu" no seu controle remoto e utilizar as teclas de navegação para selecionar a categoria desejada.</desc>
<category lang="pt">Variedades</category>
<category lang="pt">Diversos</category>
<image>
<image_name position="1">0000217661.jpg</image_name>
<image_broadcast>0000217661</image_broadcast>
<image_copyright>Image supplied by Broadcasters</image_copyright>
</image>
<video>
<colour>yes</colour>
</video>
<rating system="Advisory">
<value>Programa livre para todas as idades</value>
</rating>
</programme>
<programme start="20150607120000 -0300" stop="20150607160000 -0300" channel="XTR" program_id="0000217661" event_id="00000000000097958660" series_key="">
<title lang="pt">Novidades na sua Locadora Virtual</title>
<desc>Assista na hora que quiser e quantas vezes desejar! Para utilizar a sua Locadora Virtual, basta acessar o botão "Menu" no seu controle remoto e utilizar as teclas de navegação para selecionar a categoria desejada.</desc>
<category lang="pt">Variedades</category>
<category lang="pt">Diversos</category>
<image>
<image_name position="1">0000217661.jpg</image_name>
<image_broadcast>0000217661</image_broadcast>
<image_copyright>Image supplied by Broadcasters</image_copyright>
</image>
<video>
<colour>yes</colour>
</video>
<rating system="Advisory">
<value>Programa livre para todas as idades</value>
</rating>
</programme>
<programme start="20150607160000 -0300" stop="20150607200000 -0300" channel="XTR" program_id="0000217661" event_id="00000000000097958661" series_key="">
<title lang="pt">Novidades na sua Locadora Virtual</title>
<desc>Assista na hora que quiser e quantas vezes desejar! Para utilizar a sua Locadora Virtual, basta acessar o botão "Menu" no seu controle remoto e utilizar as teclas de navegação para selecionar a categoria desejada.</desc>
<category lang="pt">Variedades</category>
<category lang="pt">Diversos</category>
<image>
<image_name position="1">0000217661.jpg</image_name>
<image_broadcast>0000217661</image_broadcast>
<image_copyright>Image supplied by Broadcasters</image_copyright>
</image>
<video>
<colour>yes</colour>
</video>
<rating system="Advisory">
<value>Programa livre para todas as idades</value>
</rating>
</programme>
<programme start="20150607200000 -0300" stop="20150608000000 -0300" channel="XTR" program_id="0000217661" event_id="00000000000097958662" series_key="">
<title lang="pt">Novidades na sua Locadora Virtual</title>
<desc>Assista na hora que quiser e quantas vezes desejar! Para utilizar a sua Locadora Virtual, basta acessar o botão "Menu" no seu controle remoto e utilizar as teclas de navegação para selecionar a categoria desejada.</desc>
<category lang="pt">Variedades</category>
<category lang="pt">Diversos</category>
<image>
<image_name position="1">0000217661.jpg</image_name>
<image_broadcast>0000217661</image_broadcast>
<image_copyright>Image supplied by Broadcasters</image_copyright>
</image>
<video>
<colour>yes</colour>
</video>
<rating system="Advisory">
<value>Programa livre para todas as idades</value>
</rating>
</programme>
<programme start="20150608000000 -0300" stop="20150608040000 -0300" channel="XTR" program_id="0000217661" event_id="000000100557693" series_key="">
<title lang="pt">Novidades na sua Locadora Virtual</title>
<desc>Assista na hora que quiser e quantas vezes desejar! Para utilizar a sua Locadora Virtual, basta acessar o botão "Menu" no seu controle remoto e utilizar as teclas de navegação para selecionar a categoria desejada.</desc>
<category lang="pt">Variedades</category>
<category lang="pt">Diversos</category>
<image>
<image_name position="1">0000217661.jpg</image_name>
<image_broadcast>0000217661</image_broadcast>
<image_copyright>Image supplied by Broadcasters</image_copyright>
</image>
<video>
<colour>yes</colour>
</video>
<rating system="Advisory">
<value>Programa livre para todas as idades</value>
</rating>
</programme>
<programme start="20150608040000 -0300" stop="20150608080000 -0300" channel="XTR" program_id="0000217661" event_id="000000100557694" series_key="">
<title lang="pt">Novidades na sua Locadora Virtual</title>
<desc>Assista na hora que quiser e quantas vezes desejar! Para utilizar a sua Locadora Virtual, basta acessar o botão "Menu" no seu controle remoto e utilizar as teclas de navegação para selecionar a categoria desejada.</desc>
<category lang="pt">Variedades</category>
<category lang="pt">Diversos</category>
<image>
<image_name position="1">0000217661.jpg</image_name>
<image_broadcast>0000217661</image_broadcast>
<image_copyright>Image supplied by Broadcasters</image_copyright>
</image>
<video>
<colour>yes</colour>
</video>
<rating system="Advisory">
<value>Programa livre para todas as idades</value>
</rating>
</programme>
<programme start="20150608080000 -0300" stop="20150608120000 -0300" channel="XTR" program_id="0000217661" event_id="000000100557695" series_key="">
<title lang="pt">Novidades na sua Locadora Virtual</title>
<desc>Assista na hora que quiser e quantas vezes desejar! Para utilizar a sua Locadora Virtual, basta acessar o botão "Menu" no seu controle remoto e utilizar as teclas de navegação para selecionar a categoria desejada.</desc>
<category lang="pt">Variedades</category>
<category lang="pt">Diversos</category>
<image>
<image_name position="1">0000217661.jpg</image_name>
<image_broadcast>0000217661</image_broadcast>
<image_copyright>Image supplied by Broadcasters</image_copyright>
</image>
<video>
<colour>yes</colour>
</video>
<rating system="Advisory">
<value>Programa livre para todas as idades</value>
</rating>
</programme>
<programme start="20150608120000 -0300" stop="20150608160000 -0300" channel="XTR" program_id="0000217661" event_id="000000100557696" series_key="">
<title lang="pt">Novidades na sua Locadora Virtual</title>
<desc>Assista na hora que quiser e quantas vezes desejar! Para utilizar a sua Locadora Virtual, basta acessar o botão "Menu" no seu controle remoto e utilizar as teclas de navegação para selecionar a categoria desejada.</desc>
<category lang="pt">Variedades</category>
<category lang="pt">Diversos</category>
<image>
<image_name position="1">0000217661.jpg</image_name>
<image_broadcast>0000217661</image_broadcast>
<image_copyright>Image supplied by Broadcasters</image_copyright>
</image>
<video>
<colour>yes</colour>
</video>
<rating system="Advisory">
<value>Programa livre para todas as idades</value>
</rating>
</programme>
<programme start="20150608160000 -0300" stop="20150608200000 -0300" channel="XTR" program_id="0000217661" event_id="000000100557697" series_key="">
<title lang="pt">Novidades na sua Locadora Virtual</title>
<desc>Assista na hora que quiser e quantas vezes desejar! Para utilizar a sua Locadora Virtual, basta acessar o botão "Menu" no seu controle remoto e utilizar as teclas de navegação para selecionar a categoria desejada.</desc>
<category lang="pt">Variedades</category>
<category lang="pt">Diversos</category>
<image>
<image_name position="1">0000217661.jpg</image_name>
<image_broadcast>0000217661</image_broadcast>
<image_copyright>Image supplied by Broadcasters</image_copyright>
</image>
<video>
<colour>yes</colour>
</video>
<rating system="Advisory">
<value>Programa livre para todas as idades</value>
</rating>
</programme>
<programme start="20150608200000 -0300" stop="20150609000000 -0300" channel="XTR" program_id="0000217661" event_id="000000100557698" series_key="">
<title lang="pt">Novidades na sua Locadora Virtual</title>
<desc>Assista na hora que quiser e quantas vezes desejar! Para utilizar a sua Locadora Virtual, basta acessar o botão "Menu" no seu controle remoto e utilizar as teclas de navegação para selecionar a categoria desejada.</desc>
<category lang="pt">Variedades</category>
<category lang="pt">Diversos</category>
<image>
<image_name position="1">0000217661.jpg</image_name>
<image_broadcast>0000217661</image_broadcast>
<image_copyright>Image supplied by Broadcasters</image_copyright>
</image>
<video>
<colour>yes</colour>
</video>
<rating system="Advisory">
<value>Programa livre para todas as idades</value>
</rating>
</programme>
<programme start="20150609000000 -0300" stop="20150609040000 -0300" channel="XTR" program_id="0000217661" event_id="000000100557699" series_key="">
<title lang="pt">Novidades na sua Locadora Virtual</title>
<desc>Assista na hora que quiser e quantas vezes desejar! Para utilizar a sua Locadora Virtual, basta acessar o botão "Menu" no seu controle remoto e utilizar as teclas de navegação para selecionar a categoria desejada.</desc>
<category lang="pt">Variedades</category>
<category lang="pt">Diversos</category>
<image>
<image_name position="1">0000217661.jpg</image_name>
<image_broadcast>0000217661</image_broadcast>
<image_copyright>Image supplied by Broadcasters</image_copyright>
</image>
<video>
<colour>yes</colour>
</video>
<rating system="Advisory">
<value>Programa livre para todas as idades</value>
</rating>
</programme>
<programme start="20150609040000 -0300" stop="20150609080000 -0300" channel="XTR" program_id="0000217661" event_id="000000100557700" series_key="">
<title lang="pt">Novidades na sua Locadora Virtual</title>
<desc>Assista na hora que quiser e quantas vezes desejar! Para utilizar a sua Locadora Virtual, basta acessar o botão "Menu" no seu controle remoto e utilizar as teclas de navegação para selecionar a categoria desejada.</desc>
<category lang="pt">Variedades</category>
<category lang="pt">Diversos</category>
<image>
<image_name position="1">0000217661.jpg</image_name>
<image_broadcast>0000217661</image_broadcast>
<image_copyright>Image supplied by Broadcasters</image_copyright>
</image>
<video>
<colour>yes</colour>
</video>
<rating system="Advisory">
<value>Programa livre para todas as idades</value>
</rating>
</programme>
<programme start="20150609080000 -0300" stop="20150609120000 -0300" channel="XTR" program_id="0000217661" event_id="000000100557701" series_key="">
<title lang="pt">Novidades na sua Locadora Virtual</title>
<desc>Assista na hora que quiser e quantas vezes desejar! Para utilizar a sua Locadora Virtual, basta acessar o botão "Menu" no seu controle remoto e utilizar as teclas de navegação para selecionar a categoria desejada.</desc>
<category lang="pt">Variedades</category>
<category lang="pt">Diversos</category>
<image>
<image_name position="1">0000217661.jpg</image_name>
<image_broadcast>0000217661</image_broadcast>
<image_copyright>Image supplied by Broadcasters</image_copyright>
</image>
<video>
<colour>yes</colour>
</video>
<rating system="Advisory">
<value>Programa livre para todas as idades</value>
</rating>
</programme>
<programme start="20150609120000 -0300" stop="20150609160000 -0300" channel="XTR" program_id="0000217661" event_id="000000100557702" series_key="">
<title lang="pt">Novidades na sua Locadora Virtual</title>
<desc>Assista na hora que quiser e quantas vezes desejar! Para utilizar a sua Locadora Virtual, basta acessar o botão "Menu" no seu controle remoto e utilizar as teclas de navegação para selecionar a categoria desejada.</desc>
<category lang="pt">Variedades</category>
<category lang="pt">Diversos</category>
<image>
<image_name position="1">0000217661.jpg</image_name>
<image_broadcast>0000217661</image_broadcast>
<image_copyright>Image supplied by Broadcasters</image_copyright>
</image>
<video>
<colour>yes</colour>
</video>
<rating system="Advisory">
<value>Programa livre para todas as idades</value>
</rating>
</programme>
<programme start="20150609160000 -0300" stop="20150609200000 -0300" channel="XTR" program_id="0000217661" event_id="000000100557703" series_key="">
<title lang="pt">Novidades na sua Locadora Virtual</title>
<desc>Assista na hora que quiser e quantas vezes desejar! Para utilizar a sua Locadora Virtual, basta acessar o botão "Menu" no seu controle remoto e utilizar as teclas de navegação para selecionar a categoria desejada.</desc>
<category lang="pt">Variedades</category>
<category lang="pt">Diversos</category>
<image>
<image_name position="1">0000217661.jpg</image_name>
<image_broadcast>0000217661</image_broadcast>
<image_copyright>Image supplied by Broadcasters</image_copyright>
</image>
<video>
<colour>yes</colour>
</video>
<rating system="Advisory">
<value>Programa livre para todas as idades</value>
</rating>
</programme>
<programme start="20150609200000 -0300" stop="20150610000000 -0300" channel="XTR" program_id="0000217661" event_id="000000100557704" series_key="">
<title lang="pt">Novidades na sua Locadora Virtual</title>
<desc>Assista na hora que quiser e quantas vezes desejar! Para utilizar a sua Locadora Virtual, basta acessar o botão "Menu" no seu controle remoto e utilizar as teclas de navegação para selecionar a categoria desejada.</desc>
<category lang="pt">Variedades</category>
<category lang="pt">Diversos</category>
<image>
<image_name position="1">0000217661.jpg</image_name>
<image_broadcast>0000217661</image_broadcast>
<image_copyright>Image supplied by Broadcasters</image_copyright>
</image>
<video>
<colour>yes</colour>
</video>
<rating system="Advisory">
<value>Programa livre para todas as idades</value>
</rating>
</programme>
<programme start="20150610000000 -0300" stop="20150610040000 -0300" channel="XTR" program_id="0000217661" event_id="000000100557705" series_key="">
<title lang="pt">Novidades na sua Locadora Virtual</title>
<desc>Assista na hora que quiser e quantas vezes desejar! Para utilizar a sua Locadora Virtual, basta acessar o botão "Menu" no seu controle remoto e utilizar as teclas de navegação para selecionar a categoria desejada.</desc>
<category lang="pt">Variedades</category>
<category lang="pt">Diversos</category>
<image>
<image_name position="1">0000217661.jpg</image_name>
<image_broadcast>0000217661</image_broadcast>
<image_copyright>Image supplied by Broadcasters</image_copyright>
</image>
<video>
<colour>yes</colour>
</video>
<rating system="Advisory">
<value>Programa livre para todas as idades</value>
</rating>
</programme>
<programme start="20150610040000 -0300" stop="20150610080000 -0300" channel="XTR" program_id="0000217661" event_id="000000100557706" series_key="">
<title lang="pt">Novidades na sua Locadora Virtual</title>
<desc>Assista na hora que quiser e quantas vezes desejar! Para utilizar a sua Locadora Virtual, basta acessar o botão "Menu" no seu controle remoto e utilizar as teclas de navegação para selecionar a categoria desejada.</desc>
<category lang="pt">Variedades</category>
<category lang="pt">Diversos</category>
<image>
<image_name position="1">0000217661.jpg</image_name>
<image_broadcast>0000217661</image_broadcast>
<image_copyright>Image supplied by Broadcasters</image_copyright>
</image>
<video>
<colour>yes</colour>
</video>
<rating system="Advisory">
<value>Programa livre para todas as idades</value>
</rating>
</programme>
<programme start="20150610080000 -0300" stop="20150610120000 -0300" channel="XTR" program_id="0000217661" event_id="000000100557707" series_key="">
<title lang="pt">Novidades na sua Locadora Virtual</title>
<desc>Assista na hora que quiser e quantas vezes desejar! Para utilizar a sua Locadora Virtual, basta acessar o botão "Menu" no seu controle remoto e utilizar as teclas de navegação para selecionar a categoria desejada.</desc>
<category lang="pt">Variedades</category>
<category lang="pt">Diversos</category>
<image>
<image_name position="1">0000217661.jpg</image_name>
<image_broadcast>0000217661</image_broadcast>
<image_copyright>Image supplied by Broadcasters</image_copyright>
</image>
<video>
<colour>yes</colour>
</video>
<rating system="Advisory">
<value>Programa livre para todas as idades</value>
</rating>
</programme>
<programme start="20150610120000 -0300" stop="20150610160000 -0300" channel="XTR" program_id="0000217661" event_id="000000100557708" series_key="">
<title lang="pt">Novidades na sua Locadora Virtual</title>
<desc>Assista na hora que quiser e quantas vezes desejar! Para utilizar a sua Locadora Virtual, basta acessar o botão "Menu" no seu controle remoto e utilizar as teclas de navegação para selecionar a categoria desejada.</desc>
<category lang="pt">Variedades</category>
<category lang="pt">Diversos</category>
<image>
<image_name position="1">0000217661.jpg</image_name>
<image_broadcast>0000217661</image_broadcast>
<image_copyright>Image supplied by Broadcasters</image_copyright>
</image>
<video>
<colour>yes</colour>
</video>
<rating system="Advisory">
<value>Programa livre para todas as idades</value>
</rating>
</programme>
<programme start="20150610160000 -0300" stop="20150610200000 -0300" channel="XTR" program_id="0000217661" event_id="000000100557709" series_key="">
<title lang="pt">Novidades na sua Locadora Virtual</title>
<desc>Assista na hora que quiser e quantas vezes desejar! Para utilizar a sua Locadora Virtual, basta acessar o botão "Menu" no seu controle remoto e utilizar as teclas de navegação para selecionar a categoria desejada.</desc>
<category lang="pt">Variedades</category>
<category lang="pt">Diversos</category>
<image>
<image_name position="1">0000217661.jpg</image_name>
<image_broadcast>0000217661</image_broadcast>
<image_copyright>Image supplied by Broadcasters</image_copyright>
</image>
<video>
<colour>yes</colour>
</video>
<rating system="Advisory">
<value>Programa livre para todas as idades</value>
</rating>
</programme>
<programme start="20150610200000 -0300" stop="20150611000000 -0300" channel="XTR" program_id="0000217661" event_id="000000100557710" series_key="">
<title lang="pt">Novidades na sua Locadora Virtual</title>
<desc>Assista na hora que quiser e quantas vezes desejar! Para utilizar a sua Locadora Virtual, basta acessar o botão "Menu" no seu controle remoto e utilizar as teclas de navegação para selecionar a categoria desejada.</desc>
<category lang="pt">Variedades</category>
<category lang="pt">Diversos</category>
<image>
<image_name position="1">0000217661.jpg</image_name>
<image_broadcast>0000217661</image_broadcast>
<image_copyright>Image supplied by Broadcasters</image_copyright>
</image>
<video>
<colour>yes</colour>
</video>
<rating system="Advisory">
<value>Programa livre para todas as idades</value>
</rating>
</programme>
<programme start="20150611000000 -0300" stop="20150611040000 -0300" channel="XTR" program_id="0000217661" event_id="000000100557711" series_key="">
<title lang="pt">Novidades na sua Locadora Virtual</title>
<desc>Assista na hora que quiser e quantas vezes desejar! Para utilizar a sua Locadora Virtual, basta acessar o botão "Menu" no seu controle remoto e utilizar as teclas de navegação para selecionar a categoria desejada.</desc>
<category lang="pt">Variedades</category>
<category lang="pt">Diversos</category>
<image>
<image_name position="1">0000217661.jpg</image_name>
<image_broadcast>0000217661</image_broadcast>
<image_copyright>Image supplied by Broadcasters</image_copyright>
</image>
<video>
<colour>yes</colour>
</video>
<rating system="Advisory">
<value>Programa livre para todas as idades</value>
</rating>
</programme>
<programme start="20150611040000 -0300" stop="20150611080000 -0300" channel="XTR" program_id="0000217661" event_id="000000100557712" series_key="">
<title lang="pt">Novidades na sua Locadora Virtual</title>
<desc>Assista na hora que quiser e quantas vezes desejar! Para utilizar a sua Locadora Virtual, basta acessar o botão "Menu" no seu controle remoto e utilizar as teclas de navegação para selecionar a categoria desejada.</desc>
<category lang="pt">Variedades</category>
<category lang="pt">Diversos</category>
<image>
<image_name position="1">0000217661.jpg</image_name>
<image_broadcast>0000217661</image_broadcast>
<image_copyright>Image supplied by Broadcasters</image_copyright>
</image>
<video>
<colour>yes</colour>
</video>
<rating system="Advisory">
<value>Programa livre para todas as idades</value>
</rating>
</programme>
<programme start="20150611080000 -0300" stop="20150611120000 -0300" channel="XTR" program_id="0000217661" event_id="000000100557713" series_key="">
<title lang="pt">Novidades na sua Locadora Virtual</title>
<desc>Assista na hora que quiser e quantas vezes desejar! Para utilizar a sua Locadora Virtual, basta acessar o botão "Menu" no seu controle remoto e utilizar as teclas de navegação para selecionar a categoria desejada.</desc>
<category lang="pt">Variedades</category>
<category lang="pt">Diversos</category>
<image>
<image_name position="1">0000217661.jpg</image_name>
<image_broadcast>0000217661</image_broadcast>
<image_copyright>Image supplied by Broadcasters</image_copyright>
</image>
<video>
<colour>yes</colour>
</video>
<rating system="Advisory">
<value>Programa livre para todas as idades</value>
</rating>
</programme>
<programme start="20150611120000 -0300" stop="20150611160000 -0300" channel="XTR" program_id="0000217661" event_id="000000100557714" series_key="">
<title lang="pt">Novidades na sua Locadora Virtual</title>
<desc>Assista na hora que quiser e quantas vezes desejar! Para utilizar a sua Locadora Virtual, basta acessar o botão "Menu" no seu controle remoto e utilizar as teclas de navegação para selecionar a categoria desejada.</desc>
<category lang="pt">Variedades</category>
<category lang="pt">Diversos</category>
<image>
<image_name position="1">0000217661.jpg</image_name>
<image_broadcast>0000217661</image_broadcast>
<image_copyright>Image supplied by Broadcasters</image_copyright>
</image>
<video>
<colour>yes</colour>
</video>
<rating system="Advisory">
<value>Programa livre para todas as idades</value>
</rating>
</programme>
<programme start="20150611160000 -0300" stop="20150611200000 -0300" channel="XTR" program_id="0000217661" event_id="000000100557715" series_key="">
<title lang="pt">Novidades na sua Locadora Virtual</title>
<desc>Assista na hora que quiser e quantas vezes desejar! Para utilizar a sua Locadora Virtual, basta acessar o botão "Menu" no seu controle remoto e utilizar as teclas de navegação para selecionar a categoria desejada.</desc>
<category lang="pt">Variedades</category>
<category lang="pt">Diversos</category>
<image>
<image_name position="1">0000217661.jpg</image_name>
<image_broadcast>0000217661</image_broadcast>
<image_copyright>Image supplied by Broadcasters</image_copyright>
</image>
<video>
<colour>yes</colour>
</video>
<rating system="Advisory">
<value>Programa livre para todas as idades</value>
</rating>
</programme>
<programme start="20150611200000 -0300" stop="20150612000000 -0300" channel="XTR" program_id="0000217661" event_id="000000100557716" series_key="">
<title lang="pt">Novidades na sua Locadora Virtual</title>
<desc>Assista na hora que quiser e quantas vezes desejar! Para utilizar a sua Locadora Virtual, basta acessar o botão "Menu" no seu controle remoto e utilizar as teclas de navegação para selecionar a categoria desejada.</desc>
<category lang="pt">Variedades</category>
<category lang="pt">Diversos</category>
<image>
<image_name position="1">0000217661.jpg</image_name>
<image_broadcast>0000217661</image_broadcast>
<image_copyright>Image supplied by Broadcasters</image_copyright>
</image>
<video>
<colour>yes</colour>
</video>
<rating system="Advisory">
<value>Programa livre para todas as idades</value>
</rating>
</programme>
<programme start="20150612000000 -0300" stop="20150612040000 -0300" channel="XTR" program_id="0000217661" event_id="000000100557717" series_key="">
<title lang="pt">Novidades na sua Locadora Virtual</title>
<desc>Assista na hora que quiser e quantas vezes desejar! Para utilizar a sua Locadora Virtual, basta acessar o botão "Menu" no seu controle remoto e utilizar as teclas de navegação para selecionar a categoria desejada.</desc>
<category lang="pt">Variedades</category>
<category lang="pt">Diversos</category>
<image>
<image_name position="1">0000217661.jpg</image_name>
<image_broadcast>0000217661</image_broadcast>
<image_copyright>Image supplied by Broadcasters</image_copyright>
</image>
<video>
<colour>yes</colour>
</video>
<rating system="Advisory">
<value>Programa livre para todas as idades</value>
</rating>
</programme>
<programme start="20150612040000 -0300" stop="20150612080000 -0300" channel="XTR" program_id="0000217661" event_id="000000100557718" series_key="">
<title lang="pt">Novidades na sua Locadora Virtual</title>
<desc>Assista na hora que quiser e quantas vezes desejar! Para utilizar a sua Locadora Virtual, basta acessar o botão "Menu" no seu controle remoto e utilizar as teclas de navegação para selecionar a categoria desejada.</desc>
<category lang="pt">Variedades</category>
<category lang="pt">Diversos</category>
<image>
<image_name position="1">0000217661.jpg</image_name>
<image_broadcast>0000217661</image_broadcast>
<image_copyright>Image supplied by Broadcasters</image_copyright>
</image>
<video>
<colour>yes</colour>
</video>
<rating system="Advisory">
<value>Programa livre para todas as idades</value>
</rating>
</programme>
<programme start="20150612080000 -0300" stop="20150612120000 -0300" channel="XTR" program_id="0000217661" event_id="000000100557719" series_key="">
<title lang="pt">Novidades na sua Locadora Virtual</title>
<desc>Assista na hora que quiser e quantas vezes desejar! Para utilizar a sua Locadora Virtual, basta acessar o botão "Menu" no seu controle remoto e utilizar as teclas de navegação para selecionar a categoria desejada.</desc>
<category lang="pt">Variedades</category>
<category lang="pt">Diversos</category>
<image>
<image_name position="1">0000217661.jpg</image_name>
<image_broadcast>0000217661</image_broadcast>
<image_copyright>Image supplied by Broadcasters</image_copyright>
</image>
<video>
<colour>yes</colour>
</video>
<rating system="Advisory">
<value>Programa livre para todas as idades</value>
</rating>
</programme>
<programme start="20150612120000 -0300" stop="20150612160000 -0300" channel="XTR" program_id="0000217661" event_id="000000100557720" series_key="">
<title lang="pt">Novidades na sua Locadora Virtual</title>
<desc>Assista na hora que quiser e quantas vezes desejar! Para utilizar a sua Locadora Virtual, basta acessar o botão "Menu" no seu controle remoto e utilizar as teclas de navegação para selecionar a categoria desejada.</desc>
<category lang="pt">Variedades</category>
<category lang="pt">Diversos</category>
<image>
<image_name position="1">0000217661.jpg</image_name>
<image_broadcast>0000217661</image_broadcast>
<image_copyright>Image supplied by Broadcasters</image_copyright>
</image>
<video>
<colour>yes</colour>
</video>
<rating system="Advisory">
<value>Programa livre para todas as idades</value>
</rating>
</programme>
<programme start="20150612160000 -0300" stop="20150612200000 -0300" channel="XTR" program_id="0000217661" event_id="000000100557721" series_key="">
<title lang="pt">Novidades na sua Locadora Virtual</title>
<desc>Assista na hora que quiser e quantas vezes desejar! Para utilizar a sua Locadora Virtual, basta acessar o botão "Menu" no seu controle remoto e utilizar as teclas de navegação para selecionar a categoria desejada.</desc>
<category lang="pt">Variedades</category>
<category lang="pt">Diversos</category>
<image>
<image_name position="1">0000217661.jpg</image_name>
<image_broadcast>0000217661</image_broadcast>
<image_copyright>Image supplied by Broadcasters</image_copyright>
</image>
<video>
<colour>yes</colour>
</video>
<rating system="Advisory">
<value>Programa livre para todas as idades</value>
</rating>
</programme>
<programme start="20150612200000 -0300" stop="20150613000000 -0300" channel="XTR" program_id="0000217661" event_id="000000100557722" series_key="">
<title lang="pt">Novidades na sua Locadora Virtual</title>
<desc>Assista na hora que quiser e quantas vezes desejar! Para utilizar a sua Locadora Virtual, basta acessar o botão "Menu" no seu controle remoto e utilizar as teclas de navegação para selecionar a categoria desejada.</desc>
<category lang="pt">Variedades</category>
<category lang="pt">Diversos</category>
<image>
<image_name position="1">0000217661.jpg</image_name>
<image_broadcast>0000217661</image_broadcast>
<image_copyright>Image supplied by Broadcasters</image_copyright>
</image>
<video>
<colour>yes</colour>
</video>
<rating system="Advisory">
<value>Programa livre para todas as idades</value>
</rating>
</programme>
<programme start="20150613000000 -0300" stop="20150613040000 -0300" channel="XTR" program_id="0000217661" event_id="000000100557723" series_key="">
<title lang="pt">Novidades na sua Locadora Virtual</title>
<desc>Assista na hora que quiser e quantas vezes desejar! Para utilizar a sua Locadora Virtual, basta acessar o botão "Menu" no seu controle remoto e utilizar as teclas de navegação para selecionar a categoria desejada.</desc>
<category lang="pt">Variedades</category>
<category lang="pt">Diversos</category>
<image>
<image_name position="1">0000217661.jpg</image_name>
<image_broadcast>0000217661</image_broadcast>
<image_copyright>Image supplied by Broadcasters</image_copyright>
</image>
<video>
<colour>yes</colour>
</video>
<rating system="Advisory">
<value>Programa livre para todas as idades</value>
</rating>
</programme>
<programme start="20150613040000 -0300" stop="20150613080000 -0300" channel="XTR" program_id="0000217661" event_id="000000100557724" series_key="">
<title lang="pt">Novidades na sua Locadora Virtual</title>
<desc>Assista na hora que quiser e quantas vezes desejar! Para utilizar a sua Locadora Virtual, basta acessar o botão "Menu" no seu controle remoto e utilizar as teclas de navegação para selecionar a categoria desejada.</desc>
<category lang="pt">Variedades</category>
<category lang="pt">Diversos</category>
<image>
<image_name position="1">0000217661.jpg</image_name>
<image_broadcast>0000217661</image_broadcast>
<image_copyright>Image supplied by Broadcasters</image_copyright>
</image>
<video>
<colour>yes</colour>
</video>
<rating system="Advisory">
<value>Programa livre para todas as idades</value>
</rating>
</programme>
<programme start="20150613080000 -0300" stop="20150613120000 -0300" channel="XTR" program_id="0000217661" event_id="000000100557725" series_key="">
<title lang="pt">Novidades na sua Locadora Virtual</title>
<desc>Assista na hora que quiser e quantas vezes desejar! Para utilizar a sua Locadora Virtual, basta acessar o botão "Menu" no seu controle remoto e utilizar as teclas de navegação para selecionar a categoria desejada.</desc>
<category lang="pt">Variedades</category>
<category lang="pt">Diversos</category>
<image>
<image_name position="1">0000217661.jpg</image_name>
<image_broadcast>0000217661</image_broadcast>
<image_copyright>Image supplied by Broadcasters</image_copyright>
</image>
<video>
<colour>yes</colour>
</video>
<rating system="Advisory">
<value>Programa livre para todas as idades</value>
</rating>
</programme>
<programme start="20150613120000 -0300" stop="20150613160000 -0300" channel="XTR" program_id="0000217661" event_id="000000100557726" series_key="">
<title lang="pt">Novidades na sua Locadora Virtual</title>
<desc>Assista na hora que quiser e quantas vezes desejar! Para utilizar a sua Locadora Virtual, basta acessar o botão "Menu" no seu controle remoto e utilizar as teclas de navegação para selecionar a categoria desejada.</desc>
<category lang="pt">Variedades</category>
<category lang="pt">Diversos</category>
<image>
<image_name position="1">0000217661.jpg</image_name>
<image_broadcast>0000217661</image_broadcast>
<image_copyright>Image supplied by Broadcasters</image_copyright>
</image>
<video>
<colour>yes</colour>
</video>
<rating system="Advisory">
<value>Programa livre para todas as idades</value>
</rating>
</programme>
<programme start="20150613160000 -0300" stop="20150613200000 -0300" channel="XTR" program_id="0000217661" event_id="000000100557727" series_key="">
<title lang="pt">Novidades na sua Locadora Virtual</title>
<desc>Assista na hora que quiser e quantas vezes desejar! Para utilizar a sua Locadora Virtual, basta acessar o botão "Menu" no seu controle remoto e utilizar as teclas de navegação para selecionar a categoria desejada.</desc>
<category lang="pt">Variedades</category>
<category lang="pt">Diversos</category>
<image>
<image_name position="1">0000217661.jpg</image_name>
<image_broadcast>0000217661</image_broadcast>
<image_copyright>Image supplied by Broadcasters</image_copyright>
</image>
<video>
<colour>yes</colour>
</video>
<rating system="Advisory">
<value>Programa livre para todas as idades</value>
</rating>
</programme>
<programme start="20150613200000 -0300" stop="20150614000000 -0300" channel="XTR" program_id="0000217661" event_id="000000100557728" series_key="">
<title lang="pt">Novidades na sua Locadora Virtual</title>
<desc>Assista na hora que quiser e quantas vezes desejar! Para utilizar a sua Locadora Virtual, basta acessar o botão "Menu" no seu controle remoto e utilizar as teclas de navegação para selecionar a categoria desejada.</desc>
<category lang="pt">Variedades</category>
<category lang="pt">Diversos</category>
<image>
<image_name position="1">0000217661.jpg</image_name>
<image_broadcast>0000217661</image_broadcast>
<image_copyright>Image supplied by Broadcasters</image_copyright>
</image>
<video>
<colour>yes</colour>
</video>
<rating system="Advisory">
<value>Programa livre para todas as idades</value>
</rating>
</programme>
<programme start="20150614000000 -0300" stop="20150614040000 -0300" channel="XTR" program_id="0000217661" event_id="000000100557729" series_key="">
<title lang="pt">Novidades na sua Locadora Virtual</title>
<desc>Assista na hora que quiser e quantas vezes desejar! Para utilizar a sua Locadora Virtual, basta acessar o botão "Menu" no seu controle remoto e utilizar as teclas de navegação para selecionar a categoria desejada.</desc>
<category lang="pt">Variedades</category>
<category lang="pt">Diversos</category>
<image>
<image_name position="1">0000217661.jpg</image_name>
<image_broadcast>0000217661</image_broadcast>
<image_copyright>Image supplied by Broadcasters</image_copyright>
</image>
<video>
<colour>yes</colour>
</video>
<rating system="Advisory">
<value>Programa livre para todas as idades</value>
</rating>
</programme>
<programme start="20150614040000 -0300" stop="20150614080000 -0300" channel="XTR" program_id="0000217661" event_id="000000100557730" series_key="">
<title lang="pt">Novidades na sua Locadora Virtual</title>
<desc>Assista na hora que quiser e quantas vezes desejar! Para utilizar a sua Locadora Virtual, basta acessar o botão "Menu" no seu controle remoto e utilizar as teclas de navegação para selecionar a categoria desejada.</desc>
<category lang="pt">Variedades</category>
<category lang="pt">Diversos</category>
<image>
<image_name position="1">0000217661.jpg</image_name>
<image_broadcast>0000217661</image_broadcast>
<image_copyright>Image supplied by Broadcasters</image_copyright>
</image>
<video>
<colour>yes</colour>
</video>
<rating system="Advisory">
<value>Programa livre para todas as idades</value>
</rating>
</programme>
<programme start="20150614080000 -0300" stop="20150614120000 -0300" channel="XTR" program_id="0000217661" event_id="000000100557731" series_key="">
<title lang="pt">Novidades na sua Locadora Virtual</title>
<desc>Assista na hora que quiser e quantas vezes desejar! Para utilizar a sua Locadora Virtual, basta acessar o botão "Menu" no seu controle remoto e utilizar as teclas de navegação para selecionar a categoria desejada.</desc>
<category lang="pt">Variedades</category>
<category lang="pt">Diversos</category>
<image>
<image_name position="1">0000217661.jpg</image_name>
<image_broadcast>0000217661</image_broadcast>
<image_copyright>Image supplied by Broadcasters</image_copyright>
</image>
<video>
<colour>yes</colour>
</video>
<rating system="Advisory">
<value>Programa livre para todas as idades</value>
</rating>
</programme>
<programme start="20150614120000 -0300" stop="20150614160000 -0300" channel="XTR" program_id="0000217661" event_id="000000100557732" series_key="">
<title lang="pt">Novidades na sua Locadora Virtual</title>
<desc>Assista na hora que quiser e quantas vezes desejar! Para utilizar a sua Locadora Virtual, basta acessar o botão "Menu" no seu controle remoto e utilizar as teclas de navegação para selecionar a categoria desejada.</desc>
<category lang="pt">Variedades</category>
<category lang="pt">Diversos</category>
<image>
<image_name position="1">0000217661.jpg</image_name>
<image_broadcast>0000217661</image_broadcast>
<image_copyright>Image supplied by Broadcasters</image_copyright>
</image>
<video>
<colour>yes</colour>
</video>
<rating system="Advisory">
<value>Programa livre para todas as idades</value>
</rating>
</programme>
<programme start="20150614160000 -0300" stop="20150614200000 -0300" channel="XTR" program_id="0000217661" event_id="000000100557733" series_key="">
<title lang="pt">Novidades na sua Locadora Virtual</title>
<desc>Assista na hora que quiser e quantas vezes desejar! Para utilizar a sua Locadora Virtual, basta acessar o botão "Menu" no seu controle remoto e utilizar as teclas de navegação para selecionar a categoria desejada.</desc>
<category lang="pt">Variedades</category>
<category lang="pt">Diversos</category>
<image>
<image_name position="1">0000217661.jpg</image_name>
<image_broadcast>0000217661</image_broadcast>
<image_copyright>Image supplied by Broadcasters</image_copyright>
</image>
<video>
<colour>yes</colour>
</video>
<rating system="Advisory">
<value>Programa livre para todas as idades</value>
</rating>
</programme>
<programme start="20150614200000 -0300" stop="20150615000000 -0300" channel="XTR" program_id="0000217661" event_id="000000100557734" series_key="">
<title lang="pt">Novidades na sua Locadora Virtual</title>
<desc>Assista na hora que quiser e quantas vezes desejar! Para utilizar a sua Locadora Virtual, basta acessar o botão "Menu" no seu controle remoto e utilizar as teclas de navegação para selecionar a categoria desejada.</desc>
<category lang="pt">Variedades</category>
<category lang="pt">Diversos</category>
<image>
<image_name position="1">0000217661.jpg</image_name>
<image_broadcast>0000217661</image_broadcast>
<image_copyright>Image supplied by Broadcasters</image_copyright>
</image>
<video>
<colour>yes</colour>
</video>
<rating system="Advisory">
<value>Programa livre para todas as idades</value>
</rating>
</programme>
<programme start="20150615000000 -0300" stop="20150615040000 -0300" channel="XTR" program_id="0000217661" event_id="000000100557735" series_key="">
<title lang="pt">Novidades na sua Locadora Virtual</title>
<desc>Assista na hora que quiser e quantas vezes desejar! Para utilizar a sua Locadora Virtual, basta acessar o botão "Menu" no seu controle remoto e utilizar as teclas de navegação para selecionar a categoria desejada.</desc>
<category lang="pt">Variedades</category>
<category lang="pt">Diversos</category>
<image>
<image_name position="1">0000217661.jpg</image_name>
<image_broadcast>0000217661</image_broadcast>
<image_copyright>Image supplied by Broadcasters</image_copyright>
</image>
<video>
<colour>yes</colour>
</video>
<rating system="Advisory">
<value>Programa livre para todas as idades</value>
</rating>
</programme>
<programme start="20150615040000 -0300" stop="20150615080000 -0300" channel="XTR" program_id="0000217661" event_id="000000100557736" series_key="">
<title lang="pt">Novidades na sua Locadora Virtual</title>
<desc>Assista na hora que quiser e quantas vezes desejar! Para utilizar a sua Locadora Virtual, basta acessar o botão "Menu" no seu controle remoto e utilizar as teclas de navegação para selecionar a categoria desejada.</desc>
<category lang="pt">Variedades</category>
<category lang="pt">Diversos</category>
<image>
<image_name position="1">0000217661.jpg</image_name>
<image_broadcast>0000217661</image_broadcast>
<image_copyright>Image supplied by Broadcasters</image_copyright>
</image>
<video>
<colour>yes</colour>
</video>
<rating system="Advisory">
<value>Programa livre para todas as idades</value>
</rating>
</programme>
<programme start="20150615080000 -0300" stop="20150615120000 -0300" channel="XTR" program_id="0000217661" event_id="000000100557737" series_key="">
<title lang="pt">Novidades na sua Locadora Virtual</title>
<desc>Assista na hora que quiser e quantas vezes desejar! Para utilizar a sua Locadora Virtual, basta acessar o botão "Menu" no seu controle remoto e utilizar as teclas de navegação para selecionar a categoria desejada.</desc>
<category lang="pt">Variedades</category>
<category lang="pt">Diversos</category>
<image>
<image_name position="1">0000217661.jpg</image_name>
<image_broadcast>0000217661</image_broadcast>
<image_copyright>Image supplied by Broadcasters</image_copyright>
</image>
<video>
<colour>yes</colour>
</video>
<rating system="Advisory">
<value>Programa livre para todas as idades</value>
</rating>
</programme>
<programme start="20150615120000 -0300" stop="20150615160000 -0300" channel="XTR" program_id="0000217661" event_id="000000100557738" series_key="">
<title lang="pt">Novidades na sua Locadora Virtual</title>
<desc>Assista na hora que quiser e quantas vezes desejar! Para utilizar a sua Locadora Virtual, basta acessar o botão "Menu" no seu controle remoto e utilizar as teclas de navegação para selecionar a categoria desejada.</desc>
<category lang="pt">Variedades</category>
<category lang="pt">Diversos</category>
<image>
<image_name position="1">0000217661.jpg</image_name>
<image_broadcast>0000217661</image_broadcast>
<image_copyright>Image supplied by Broadcasters</image_copyright>
</image>
<video>
<colour>yes</colour>
</video>
<rating system="Advisory">
<value>Programa livre para todas as idades</value>
</rating>
</programme>
<programme start="20150615160000 -0300" stop="20150615200000 -0300" channel="XTR" program_id="0000217661" event_id="000000100557739" series_key="">
<title lang="pt">Novidades na sua Locadora Virtual</title>
<desc>Assista na hora que quiser e quantas vezes desejar! Para utilizar a sua Locadora Virtual, basta acessar o botão "Menu" no seu controle remoto e utilizar as teclas de navegação para selecionar a categoria desejada.</desc>
<category lang="pt">Variedades</category>
<category lang="pt">Diversos</category>
<image>
<image_name position="1">0000217661.jpg</image_name>
<image_broadcast>0000217661</image_broadcast>
<image_copyright>Image supplied by Broadcasters</image_copyright>
</image>
<video>
<colour>yes</colour>
</video>
<rating system="Advisory">
<value>Programa livre para todas as idades</value>
</rating>
</programme>
<programme start="20150615200000 -0300" stop="20150616000000 -0300" channel="XTR" program_id="0000217661" event_id="000000100557740" series_key="">
<title lang="pt">Novidades na sua Locadora Virtual</title>
<desc>Assista na hora que quiser e quantas vezes desejar! Para utilizar a sua Locadora Virtual, basta acessar o botão "Menu" no seu controle remoto e utilizar as teclas de navegação para selecionar a categoria desejada.</desc>
<category lang="pt">Variedades</category>
<category lang="pt">Diversos</category>
<image>
<image_name position="1">0000217661.jpg</image_name>
<image_broadcast>0000217661</image_broadcast>
<image_copyright>Image supplied by Broadcasters</image_copyright>
</image>
<video>
<colour>yes</colour>
</video>
<rating system="Advisory">
<value>Programa livre para todas as idades</value>
</rating>
</programme>
<programme start="20150616000000 -0300" stop="20150616040000 -0300" channel="XTR" program_id="0000217661" event_id="000000100557741" series_key="">
<title lang="pt">Novidades na sua Locadora Virtual</title>
<desc>Assista na hora que quiser e quantas vezes desejar! Para utilizar a sua Locadora Virtual, basta acessar o botão "Menu" no seu controle remoto e utilizar as teclas de navegação para selecionar a categoria desejada.</desc>
<category lang="pt">Variedades</category>
<category lang="pt">Diversos</category>
<image>
<image_name position="1">0000217661.jpg</image_name>
<image_broadcast>0000217661</image_broadcast>
<image_copyright>Image supplied by Broadcasters</image_copyright>
</image>
<video>
<colour>yes</colour>
</video>
<rating system="Advisory">
<value>Programa livre para todas as idades</value>
</rating>
</programme>
<programme start="20150616040000 -0300" stop="20150616080000 -0300" channel="XTR" program_id="0000217661" event_id="000000100557742" series_key="">
<title lang="pt">Novidades na sua Locadora Virtual</title>
<desc>Assista na hora que quiser e quantas vezes desejar! Para utilizar a sua Locadora Virtual, basta acessar o botão "Menu" no seu controle remoto e utilizar as teclas de navegação para selecionar a categoria desejada.</desc>
<category lang="pt">Variedades</category>
<category lang="pt">Diversos</category>
<image>
<image_name position="1">0000217661.jpg</image_name>
<image_broadcast>0000217661</image_broadcast>
<image_copyright>Image supplied by Broadcasters</image_copyright>
</image>
<video>
<colour>yes</colour>
</video>
<rating system="Advisory">
<value>Programa livre para todas as idades</value>
</rating>
</programme>
<programme start="20150616080000 -0300" stop="20150616120000 -0300" channel="XTR" program_id="0000217661" event_id="000000100557743" series_key="">
<title lang="pt">Novidades na sua Locadora Virtual</title>
<desc>Assista na hora que quiser e quantas vezes desejar! Para utilizar a sua Locadora Virtual, basta acessar o botão "Menu" no seu controle remoto e utilizar as teclas de navegação para selecionar a categoria desejada.</desc>
<category lang="pt">Variedades</category>
<category lang="pt">Diversos</category>
<image>
<image_name position="1">0000217661.jpg</image_name>
<image_broadcast>0000217661</image_broadcast>
<image_copyright>Image supplied by Broadcasters</image_copyright>
</image>
<video>
<colour>yes</colour>
</video>
<rating system="Advisory">
<value>Programa livre para todas as idades</value>
</rating>
</programme>
<programme start="20150616120000 -0300" stop="20150616160000 -0300" channel="XTR" program_id="0000217661" event_id="000000100557744" series_key="">
<title lang="pt">Novidades na sua Locadora Virtual</title>
<desc>Assista na hora que quiser e quantas vezes desejar! Para utilizar a sua Locadora Virtual, basta acessar o botão "Menu" no seu controle remoto e utilizar as teclas de navegação para selecionar a categoria desejada.</desc>
<category lang="pt">Variedades</category>
<category lang="pt">Diversos</category>
<image>
<image_name position="1">0000217661.jpg</image_name>
<image_broadcast>0000217661</image_broadcast>
<image_copyright>Image supplied by Broadcasters</image_copyright>
</image>
<video>
<colour>yes</colour>
</video>
<rating system="Advisory">
<value>Programa livre para todas as idades</value>
</rating>
</programme>
<programme start="20150616160000 -0300" stop="20150616200000 -0300" channel="XTR" program_id="0000217661" event_id="000000100557745" series_key="">
<title lang="pt">Novidades na sua Locadora Virtual</title>
<desc>Assista na hora que quiser e quantas vezes desejar! Para utilizar a sua Locadora Virtual, basta acessar o botão "Menu" no seu controle remoto e utilizar as teclas de navegação para selecionar a categoria desejada.</desc>
<category lang="pt">Variedades</category>
<category lang="pt">Diversos</category>
<image>
<image_name position="1">0000217661.jpg</image_name>
<image_broadcast>0000217661</image_broadcast>
<image_copyright>Image supplied by Broadcasters</image_copyright>
</image>
<video>
<colour>yes</colour>
</video>
<rating system="Advisory">
<value>Programa livre para todas as idades</value>
</rating>
</programme>
<programme start="20150616200000 -0300" stop="20150617000000 -0300" channel="XTR" program_id="0000217661" event_id="000000100557746" series_key="">
<title lang="pt">Novidades na sua Locadora Virtual</title>
<desc>Assista na hora que quiser e quantas vezes desejar! Para utilizar a sua Locadora Virtual, basta acessar o botão "Menu" no seu controle remoto e utilizar as teclas de navegação para selecionar a categoria desejada.</desc>
<category lang="pt">Variedades</category>
<category lang="pt">Diversos</category>
<image>
<image_name position="1">0000217661.jpg</image_name>
<image_broadcast>0000217661</image_broadcast>
<image_copyright>Image supplied by Broadcasters</image_copyright>
</image>
<video>
<colour>yes</colour>
</video>
<rating system="Advisory">
<value>Programa livre para todas as idades</value>
</rating>
</programme>
<programme start="20150617000000 -0300" stop="20150617040000 -0300" channel="XTR" program_id="0000217661" event_id="000000100557747" series_key="">
<title lang="pt">Novidades na sua Locadora Virtual</title>
<desc>Assista na hora que quiser e quantas vezes desejar! Para utilizar a sua Locadora Virtual, basta acessar o botão "Menu" no seu controle remoto e utilizar as teclas de navegação para selecionar a categoria desejada.</desc>
<category lang="pt">Variedades</category>
<category lang="pt">Diversos</category>
<image>
<image_name position="1">0000217661.jpg</image_name>
<image_broadcast>0000217661</image_broadcast>
<image_copyright>Image supplied by Broadcasters</image_copyright>
</image>
<video>
<colour>yes</colour>
</video>
<rating system="Advisory">
<value>Programa livre para todas as idades</value>
</rating>
</programme>
<programme start="20150617040000 -0300" stop="20150617080000 -0300" channel="XTR" program_id="0000217661" event_id="000000100557748" series_key="">
<title lang="pt">Novidades na sua Locadora Virtual</title>
<desc>Assista na hora que quiser e quantas vezes desejar! Para utilizar a sua Locadora Virtual, basta acessar o botão "Menu" no seu controle remoto e utilizar as teclas de navegação para selecionar a categoria desejada.</desc>
<category lang="pt">Variedades</category>
<category lang="pt">Diversos</category>
<image>
<image_name position="1">0000217661.jpg</image_name>
<image_broadcast>0000217661</image_broadcast>
<image_copyright>Image supplied by Broadcasters</image_copyright>
</image>
<video>
<colour>yes</colour>
</video>
<rating system="Advisory">
<value>Programa livre para todas as idades</value>
</rating>
</programme>
<programme start="20150617080000 -0300" stop="20150617120000 -0300" channel="XTR" program_id="0000217661" event_id="000000100557749" series_key="">
<title lang="pt">Novidades na sua Locadora Virtual</title>
<desc>Assista na hora que quiser e quantas vezes desejar! Para utilizar a sua Locadora Virtual, basta acessar o botão "Menu" no seu controle remoto e utilizar as teclas de navegação para selecionar a categoria desejada.</desc>
<category lang="pt">Variedades</category>
<category lang="pt">Diversos</category>
<image>
<image_name position="1">0000217661.jpg</image_name>
<image_broadcast>0000217661</image_broadcast>
<image_copyright>Image supplied by Broadcasters</image_copyright>
</image>
<video>
<colour>yes</colour>
</video>
<rating system="Advisory">
<value>Programa livre para todas as idades</value>
</rating>
</programme>
<programme start="20150617120000 -0300" stop="20150617160000 -0300" channel="XTR" program_id="0000217661" event_id="000000100557750" series_key="">
<title lang="pt">Novidades na sua Locadora Virtual</title>
<desc>Assista na hora que quiser e quantas vezes desejar! Para utilizar a sua Locadora Virtual, basta acessar o botão "Menu" no seu controle remoto e utilizar as teclas de navegação para selecionar a categoria desejada.</desc>
<category lang="pt">Variedades</category>
<category lang="pt">Diversos</category>
<image>
<image_name position="1">0000217661.jpg</image_name>
<image_broadcast>0000217661</image_broadcast>
<image_copyright>Image supplied by Broadcasters</image_copyright>
</image>
<video>
<colour>yes</colour>
</video>
<rating system="Advisory">
<value>Programa livre para todas as idades</value>
</rating>
</programme>
<programme start="20150617160000 -0300" stop="20150617200000 -0300" channel="XTR" program_id="0000217661" event_id="000000100557751" series_key="">
<title lang="pt">Novidades na sua Locadora Virtual</title>
<desc>Assista na hora que quiser e quantas vezes desejar! Para utilizar a sua Locadora Virtual, basta acessar o botão "Menu" no seu controle remoto e utilizar as teclas de navegação para selecionar a categoria desejada.</desc>
<category lang="pt">Variedades</category>
<category lang="pt">Diversos</category>
<image>
<image_name position="1">0000217661.jpg</image_name>
<image_broadcast>0000217661</image_broadcast>
<image_copyright>Image supplied by Broadcasters</image_copyright>
</image>
<video>
<colour>yes</colour>
</video>
<rating system="Advisory">
<value>Programa livre para todas as idades</value>
</rating>
</programme>
<programme start="20150617200000 -0300" stop="20150618000000 -0300" channel="XTR" program_id="0000217661" event_id="000000100557752" series_key="">
<title lang="pt">Novidades na sua Locadora Virtual</title>
<desc>Assista na hora que quiser e quantas vezes desejar! Para utilizar a sua Locadora Virtual, basta acessar o botão "Menu" no seu controle remoto e utilizar as teclas de navegação para selecionar a categoria desejada.</desc>
<category lang="pt">Variedades</category>
<category lang="pt">Diversos</category>
<image>
<image_name position="1">0000217661.jpg</image_name>
<image_broadcast>0000217661</image_broadcast>
<image_copyright>Image supplied by Broadcasters</image_copyright>
</image>
<video>
<colour>yes</colour>
</video>
<rating system="Advisory">
<value>Programa livre para todas as idades</value>
</rating>
</programme>
<programme start="20150618000000 -0300" stop="20150618040000 -0300" channel="XTR" program_id="0000217661" event_id="000000100557753" series_key="">
<title lang="pt">Novidades na sua Locadora Virtual</title>
<desc>Assista na hora que quiser e quantas vezes desejar! Para utilizar a sua Locadora Virtual, basta acessar o botão "Menu" no seu controle remoto e utilizar as teclas de navegação para selecionar a categoria desejada.</desc>
<category lang="pt">Variedades</category>
<category lang="pt">Diversos</category>
<image>
<image_name position="1">0000217661.jpg</image_name>
<image_broadcast>0000217661</image_broadcast>
<image_copyright>Image supplied by Broadcasters</image_copyright>
</image>
<video>
<colour>yes</colour>
</video>
<rating system="Advisory">
<value>Programa livre para todas as idades</value>
</rating>
</programme>
<programme start="20150618040000 -0300" stop="20150618080000 -0300" channel="XTR" program_id="0000217661" event_id="000000100557754" series_key="">
<title lang="pt">Novidades na sua Locadora Virtual</title>
<desc>Assista na hora que quiser e quantas vezes desejar! Para utilizar a sua Locadora Virtual, basta acessar o botão "Menu" no seu controle remoto e utilizar as teclas de navegação para selecionar a categoria desejada.</desc>
<category lang="pt">Variedades</category>
<category lang="pt">Diversos</category>
<image>
<image_name position="1">0000217661.jpg</image_name>
<image_broadcast>0000217661</image_broadcast>
<image_copyright>Image supplied by Broadcasters</image_copyright>
</image>
<video>
<colour>yes</colour>
</video>
<rating system="Advisory">
<value>Programa livre para todas as idades</value>
</rating>
</programme>
<programme start="20150618080000 -0300" stop="20150618120000 -0300" channel="XTR" program_id="0000217661" event_id="000000100557755" series_key="">
<title lang="pt">Novidades na sua Locadora Virtual</title>
<desc>Assista na hora que quiser e quantas vezes desejar! Para utilizar a sua Locadora Virtual, basta acessar o botão "Menu" no seu controle remoto e utilizar as teclas de navegação para selecionar a categoria desejada.</desc>
<category lang="pt">Variedades</category>
<category lang="pt">Diversos</category>
<image>
<image_name position="1">0000217661.jpg</image_name>
<image_broadcast>0000217661</image_broadcast>
<image_copyright>Image supplied by Broadcasters</image_copyright>
</image>
<video>
<colour>yes</colour>
</video>
<rating system="Advisory">
<value>Programa livre para todas as idades</value>
</rating>
</programme>
<programme start="20150618120000 -0300" stop="20150618160000 -0300" channel="XTR" program_id="0000217661" event_id="000000100557756" series_key="">
<title lang="pt">Novidades na sua Locadora Virtual</title>
<desc>Assista na hora que quiser e quantas vezes desejar! Para utilizar a sua Locadora Virtual, basta acessar o botão "Menu" no seu controle remoto e utilizar as teclas de navegação para selecionar a categoria desejada.</desc>
<category lang="pt">Variedades</category>
<category lang="pt">Diversos</category>
<image>
<image_name position="1">0000217661.jpg</image_name>
<image_broadcast>0000217661</image_broadcast>
<image_copyright>Image supplied by Broadcasters</image_copyright>
</image>
<video>
<colour>yes</colour>
</video>
<rating system="Advisory">
<value>Programa livre para todas as idades</value>
</rating>
</programme>
<programme start="20150618160000 -0300" stop="20150618200000 -0300" channel="XTR" program_id="0000217661" event_id="000000100557757" series_key="">
<title lang="pt">Novidades na sua Locadora Virtual</title>
<desc>Assista na hora que quiser e quantas vezes desejar! Para utilizar a sua Locadora Virtual, basta acessar o botão "Menu" no seu controle remoto e utilizar as teclas de navegação para selecionar a categoria desejada.</desc>
<category lang="pt">Variedades</category>
<category lang="pt">Diversos</category>
<image>
<image_name position="1">0000217661.jpg</image_name>
<image_broadcast>0000217661</image_broadcast>
<image_copyright>Image supplied by Broadcasters</image_copyright>
</image>
<video>
<colour>yes</colour>
</video>
<rating system="Advisory">
<value>Programa livre para todas as idades</value>
</rating>
</programme>
<programme start="20150618200000 -0300" stop="20150619000000 -0300" channel="XTR" program_id="0000217661" event_id="000000100557758" series_key="">
<title lang="pt">Novidades na sua Locadora Virtual</title>
<desc>Assista na hora que quiser e quantas vezes desejar! Para utilizar a sua Locadora Virtual, basta acessar o botão "Menu" no seu controle remoto e utilizar as teclas de navegação para selecionar a categoria desejada.</desc>
<category lang="pt">Variedades</category>
<category lang="pt">Diversos</category>
<image>
<image_name position="1">0000217661.jpg</image_name>
<image_broadcast>0000217661</image_broadcast>
<image_copyright>Image supplied by Broadcasters</image_copyright>
</image>
<video>
<colour>yes</colour>
</video>
<rating system="Advisory">
<value>Programa livre para todas as idades</value>
</rating>
</programme>
<programme start="20150619000000 -0300" stop="20150619040000 -0300" channel="XTR" program_id="0000217661" event_id="000000100557759" series_key="">
<title lang="pt">Novidades na sua Locadora Virtual</title>
<desc>Assista na hora que quiser e quantas vezes desejar! Para utilizar a sua Locadora Virtual, basta acessar o botão "Menu" no seu controle remoto e utilizar as teclas de navegação para selecionar a categoria desejada.</desc>
<category lang="pt">Variedades</category>
<category lang="pt">Diversos</category>
<image>
<image_name position="1">0000217661.jpg</image_name>
<image_broadcast>0000217661</image_broadcast>
<image_copyright>Image supplied by Broadcasters</image_copyright>
</image>
<video>
<colour>yes</colour>
</video>
<rating system="Advisory">
<value>Programa livre para todas as idades</value>
</rating>
</programme>
<programme start="20150619040000 -0300" stop="20150619080000 -0300" channel="XTR" program_id="0000217661" event_id="000000100557760" series_key="">
<title lang="pt">Novidades na sua Locadora Virtual</title>
<desc>Assista na hora que quiser e quantas vezes desejar! Para utilizar a sua Locadora Virtual, basta acessar o botão "Menu" no seu controle remoto e utilizar as teclas de navegação para selecionar a categoria desejada.</desc>
<category lang="pt">Variedades</category>
<category lang="pt">Diversos</category>
<image>
<image_name position="1">0000217661.jpg</image_name>
<image_broadcast>0000217661</image_broadcast>
<image_copyright>Image supplied by Broadcasters</image_copyright>
</image>
<video>
<colour>yes</colour>
</video>
<rating system="Advisory">
<value>Programa livre para todas as idades</value>
</rating>
</programme>
<programme start="20150619080000 -0300" stop="20150619120000 -0300" channel="XTR" program_id="0000217661" event_id="000000100557761" series_key="">
<title lang="pt">Novidades na sua Locadora Virtual</title>
<desc>Assista na hora que quiser e quantas vezes desejar! Para utilizar a sua Locadora Virtual, basta acessar o botão "Menu" no seu controle remoto e utilizar as teclas de navegação para selecionar a categoria desejada.</desc>
<category lang="pt">Variedades</category>
<category lang="pt">Diversos</category>
<image>
<image_name position="1">0000217661.jpg</image_name>
<image_broadcast>0000217661</image_broadcast>
<image_copyright>Image supplied by Broadcasters</image_copyright>
</image>
<video>
<colour>yes</colour>
</video>
<rating system="Advisory">
<value>Programa livre para todas as idades</value>
</rating>
</programme>
<programme start="20150619120000 -0300" stop="20150619160000 -0300" channel="XTR" program_id="0000217661" event_id="000000100557762" series_key="">
<title lang="pt">Novidades na sua Locadora Virtual</title>
<desc>Assista na hora que quiser e quantas vezes desejar! Para utilizar a sua Locadora Virtual, basta acessar o botão "Menu" no seu controle remoto e utilizar as teclas de navegação para selecionar a categoria desejada.</desc>
<category lang="pt">Variedades</category>
<category lang="pt">Diversos</category>
<image>
<image_name position="1">0000217661.jpg</image_name>
<image_broadcast>0000217661</image_broadcast>
<image_copyright>Image supplied by Broadcasters</image_copyright>
</image>
<video>
<colour>yes</colour>
</video>
<rating system="Advisory">
<value>Programa livre para todas as idades</value>
</rating>
</programme>
<programme start="20150619160000 -0300" stop="20150619200000 -0300" channel="XTR" program_id="0000217661" event_id="000000100557763" series_key="">
<title lang="pt">Novidades na sua Locadora Virtual</title>
<desc>Assista na hora que quiser e quantas vezes desejar! Para utilizar a sua Locadora Virtual, basta acessar o botão "Menu" no seu controle remoto e utilizar as teclas de navegação para selecionar a categoria desejada.</desc>
<category lang="pt">Variedades</category>
<category lang="pt">Diversos</category>
<image>
<image_name position="1">0000217661.jpg</image_name>
<image_broadcast>0000217661</image_broadcast>
<image_copyright>Image supplied by Broadcasters</image_copyright>
</image>
<video>
<colour>yes</colour>
</video>
<rating system="Advisory">
<value>Programa livre para todas as idades</value>
</rating>
</programme>
<programme start="20150619200000 -0300" stop="20150620000000 -0300" channel="XTR" program_id="0000217661" event_id="000000100557764" series_key="">
<title lang="pt">Novidades na sua Locadora Virtual</title>
<desc>Assista na hora que quiser e quantas vezes desejar! Para utilizar a sua Locadora Virtual, basta acessar o botão "Menu" no seu controle remoto e utilizar as teclas de navegação para selecionar a categoria desejada.</desc>
<category lang="pt">Variedades</category>
<category lang="pt">Diversos</category>
<image>
<image_name position="1">0000217661.jpg</image_name>
<image_broadcast>0000217661</image_broadcast>
<image_copyright>Image supplied by Broadcasters</image_copyright>
</image>
<video>
<colour>yes</colour>
</video>
<rating system="Advisory">
<value>Programa livre para todas as idades</value>
</rating>
</programme>
<programme start="20150620000000 -0300" stop="20150620040000 -0300" channel="XTR" program_id="0000217661" event_id="000000100557765" series_key="">
<title lang="pt">Novidades na sua Locadora Virtual</title>
<desc>Assista na hora que quiser e quantas vezes desejar! Para utilizar a sua Locadora Virtual, basta acessar o botão "Menu" no seu controle remoto e utilizar as teclas de navegação para selecionar a categoria desejada.</desc>
<category lang="pt">Variedades</category>
<category lang="pt">Diversos</category>
<image>
<image_name position="1">0000217661.jpg</image_name>
<image_broadcast>0000217661</image_broadcast>
<image_copyright>Image supplied by Broadcasters</image_copyright>
</image>
<video>
<colour>yes</colour>
</video>
<rating system="Advisory">
<value>Programa livre para todas as idades</value>
</rating>
</programme>
<programme start="20150620040000 -0300" stop="20150620080000 -0300" channel="XTR" program_id="0000217661" event_id="000000100557766" series_key="">
<title lang="pt">Novidades na sua Locadora Virtual</title>
<desc>Assista na hora que quiser e quantas vezes desejar! Para utilizar a sua Locadora Virtual, basta acessar o botão "Menu" no seu controle remoto e utilizar as teclas de navegação para selecionar a categoria desejada.</desc>
<category lang="pt">Variedades</category>
<category lang="pt">Diversos</category>
<image>
<image_name position="1">0000217661.jpg</image_name>
<image_broadcast>0000217661</image_broadcast>
<image_copyright>Image supplied by Broadcasters</image_copyright>
</image>
<video>
<colour>yes</colour>
</video>
<rating system="Advisory">
<value>Programa livre para todas as idades</value>
</rating>
</programme>
<programme start="20150620080000 -0300" stop="20150620120000 -0300" channel="XTR" program_id="0000217661" event_id="000000100557767" series_key="">
<title lang="pt">Novidades na sua Locadora Virtual</title>
<desc>Assista na hora que quiser e quantas vezes desejar! Para utilizar a sua Locadora Virtual, basta acessar o botão "Menu" no seu controle remoto e utilizar as teclas de navegação para selecionar a categoria desejada.</desc>
<category lang="pt">Variedades</category>
<category lang="pt">Diversos</category>
<image>
<image_name position="1">0000217661.jpg</image_name>
<image_broadcast>0000217661</image_broadcast>
<image_copyright>Image supplied by Broadcasters</image_copyright>
</image>
<video>
<colour>yes</colour>
</video>
<rating system="Advisory">
<value>Programa livre para todas as idades</value>
</rating>
</programme>
<programme start="20150620120000 -0300" stop="20150620160000 -0300" channel="XTR" program_id="0000217661" event_id="000000100557768" series_key="">
<title lang="pt">Novidades na sua Locadora Virtual</title>
<desc>Assista na hora que quiser e quantas vezes desejar! Para utilizar a sua Locadora Virtual, basta acessar o botão "Menu" no seu controle remoto e utilizar as teclas de navegação para selecionar a categoria desejada.</desc>
<category lang="pt">Variedades</category>
<category lang="pt">Diversos</category>
<image>
<image_name position="1">0000217661.jpg</image_name>
<image_broadcast>0000217661</image_broadcast>
<image_copyright>Image supplied by Broadcasters</image_copyright>
</image>
<video>
<colour>yes</colour>
</video>
<rating system="Advisory">
<value>Programa livre para todas as idades</value>
</rating>
</programme>
<programme start="20150620160000 -0300" stop="20150620200000 -0300" channel="XTR" program_id="0000217661" event_id="000000100557769" series_key="">
<title lang="pt">Novidades na sua Locadora Virtual</title>
<desc>Assista na hora que quiser e quantas vezes desejar! Para utilizar a sua Locadora Virtual, basta acessar o botão "Menu" no seu controle remoto e utilizar as teclas de navegação para selecionar a categoria desejada.</desc>
<category lang="pt">Variedades</category>
<category lang="pt">Diversos</category>
<image>
<image_name position="1">0000217661.jpg</image_name>
<image_broadcast>0000217661</image_broadcast>
<image_copyright>Image supplied by Broadcasters</image_copyright>
</image>
<video>
<colour>yes</colour>
</video>
<rating system="Advisory">
<value>Programa livre para todas as idades</value>
</rating>
</programme>
<programme start="20150620200000 -0300" stop="20150621000000 -0300" channel="XTR" program_id="0000217661" event_id="000000100557770" series_key="">
<title lang="pt">Novidades na sua Locadora Virtual</title>
<desc>Assista na hora que quiser e quantas vezes desejar! Para utilizar a sua Locadora Virtual, basta acessar o botão "Menu" no seu controle remoto e utilizar as teclas de navegação para selecionar a categoria desejada.</desc>
<category lang="pt">Variedades</category>
<category lang="pt">Diversos</category>
<image>
<image_name position="1">0000217661.jpg</image_name>
<image_broadcast>0000217661</image_broadcast>
<image_copyright>Image supplied by Broadcasters</image_copyright>
</image>
<video>
<colour>yes</colour>
</video>
<rating system="Advisory">
<value>Programa livre para todas as idades</value>
</rating>
</programme>
<programme start="20150621000000 -0300" stop="20150621040000 -0300" channel="XTR" program_id="0000217661" event_id="000000100557771" series_key="">
<title lang="pt">Novidades na sua Locadora Virtual</title>
<desc>Assista na hora que quiser e quantas vezes desejar! Para utilizar a sua Locadora Virtual, basta acessar o botão "Menu" no seu controle remoto e utilizar as teclas de navegação para selecionar a categoria desejada.</desc>
<category lang="pt">Variedades</category>
<category lang="pt">Diversos</category>
<image>
<image_name position="1">0000217661.jpg</image_name>
<image_broadcast>0000217661</image_broadcast>
<image_copyright>Image supplied by Broadcasters</image_copyright>
</image>
<video>
<colour>yes</colour>
</video>
<rating system="Advisory">
<value>Programa livre para todas as idades</value>
</rating>
</programme>
<programme start="20150621040000 -0300" stop="20150621080000 -0300" channel="XTR" program_id="0000217661" event_id="000000100557772" series_key="">
<title lang="pt">Novidades na sua Locadora Virtual</title>
<desc>Assista na hora que quiser e quantas vezes desejar! Para utilizar a sua Locadora Virtual, basta acessar o botão "Menu" no seu controle remoto e utilizar as teclas de navegação para selecionar a categoria desejada.</desc>
<category lang="pt">Variedades</category>
<category lang="pt">Diversos</category>
<image>
<image_name position="1">0000217661.jpg</image_name>
<image_broadcast>0000217661</image_broadcast>
<image_copyright>Image supplied by Broadcasters</image_copyright>
</image>
<video>
<colour>yes</colour>
</video>
<rating system="Advisory">
<value>Programa livre para todas as idades</value>
</rating>
</programme>
<programme start="20150621080000 -0300" stop="20150621120000 -0300" channel="XTR" program_id="0000217661" event_id="000000100557773" series_key="">
<title lang="pt">Novidades na sua Locadora Virtual</title>
<desc>Assista na hora que quiser e quantas vezes desejar! Para utilizar a sua Locadora Virtual, basta acessar o botão "Menu" no seu controle remoto e utilizar as teclas de navegação para selecionar a categoria desejada.</desc>
<category lang="pt">Variedades</category>
<category lang="pt">Diversos</category>
<image>
<image_name position="1">0000217661.jpg</image_name>
<image_broadcast>0000217661</image_broadcast>
<image_copyright>Image supplied by Broadcasters</image_copyright>
</image>
<video>
<colour>yes</colour>
</video>
<rating system="Advisory">
<value>Programa livre para todas as idades</value>
</rating>
</programme>
<programme start="20150621120000 -0300" stop="20150621160000 -0300" channel="XTR" program_id="0000217661" event_id="000000100557774" series_key="">
<title lang="pt">Novidades na sua Locadora Virtual</title>
<desc>Assista na hora que quiser e quantas vezes desejar! Para utilizar a sua Locadora Virtual, basta acessar o botão "Menu" no seu controle remoto e utilizar as teclas de navegação para selecionar a categoria desejada.</desc>
<category lang="pt">Variedades</category>
<category lang="pt">Diversos</category>
<image>
<image_name position="1">0000217661.jpg</image_name>
<image_broadcast>0000217661</image_broadcast>
<image_copyright>Image supplied by Broadcasters</image_copyright>
</image>
<video>
<colour>yes</colour>
</video>
<rating system="Advisory">
<value>Programa livre para todas as idades</value>
</rating>
</programme>
<programme start="20150621160000 -0300" stop="20150621200000 -0300" channel="XTR" program_id="0000217661" event_id="000000100557775" series_key="">
<title lang="pt">Novidades na sua Locadora Virtual</title>
<desc>Assista na hora que quiser e quantas vezes desejar! Para utilizar a sua Locadora Virtual, basta acessar o botão "Menu" no seu controle remoto e utilizar as teclas de navegação para selecionar a categoria desejada.</desc>
<category lang="pt">Variedades</category>
<category lang="pt">Diversos</category>
<image>
<image_name position="1">0000217661.jpg</image_name>
<image_broadcast>0000217661</image_broadcast>
<image_copyright>Image supplied by Broadcasters</image_copyright>
</image>
<video>
<colour>yes</colour>
</video>
<rating system="Advisory">
<value>Programa livre para todas as idades</value>
</rating>
</programme>
<programme start="20150621200000 -0300" stop="20150622000000 -0300" channel="XTR" program_id="0000217661" event_id="000000100557776" series_key="">
<title lang="pt">Novidades na sua Locadora Virtual</title>
<desc>Assista na hora que quiser e quantas vezes desejar! Para utilizar a sua Locadora Virtual, basta acessar o botão "Menu" no seu controle remoto e utilizar as teclas de navegação para selecionar a categoria desejada.</desc>
<category lang="pt">Variedades</category>
<category lang="pt">Diversos</category>
<image>
<image_name position="1">0000217661.jpg</image_name>
<image_broadcast>0000217661</image_broadcast>
<image_copyright>Image supplied by Broadcasters</image_copyright>
</image>
<video>
<colour>yes</colour>
</video>
<rating system="Advisory">
<value>Programa livre para todas as idades</value>
</rating>
</programme>
<programme start="20150622000000 -0300" stop="20150622040000 -0300" channel="XTR" program_id="0000217661" event_id="000000100557777" series_key="">
<title lang="pt">Novidades na sua Locadora Virtual</title>
<desc>Assista na hora que quiser e quantas vezes desejar! Para utilizar a sua Locadora Virtual, basta acessar o botão "Menu" no seu controle remoto e utilizar as teclas de navegação para selecionar a categoria desejada.</desc>
<category lang="pt">Variedades</category>
<category lang="pt">Diversos</category>
<image>
<image_name position="1">0000217661.jpg</image_name>
<image_broadcast>0000217661</image_broadcast>
<image_copyright>Image supplied by Broadcasters</image_copyright>
</image>
<video>
<colour>yes</colour>
</video>
<rating system="Advisory">
<value>Programa livre para todas as idades</value>
</rating>
</programme>
<programme start="20150622040000 -0300" stop="20150622080000 -0300" channel="XTR" program_id="0000217661" event_id="000000100557778" series_key="">
<title lang="pt">Novidades na sua Locadora Virtual</title>
<desc>Assista na hora que quiser e quantas vezes desejar! Para utilizar a sua Locadora Virtual, basta acessar o botão "Menu" no seu controle remoto e utilizar as teclas de navegação para selecionar a categoria desejada.</desc>
<category lang="pt">Variedades</category>
<category lang="pt">Diversos</category>
<image>
<image_name position="1">0000217661.jpg</image_name>
<image_broadcast>0000217661</image_broadcast>
<image_copyright>Image supplied by Broadcasters</image_copyright>
</image>
<video>
<colour>yes</colour>
</video>
<rating system="Advisory">
<value>Programa livre para todas as idades</value>
</rating>
</programme>
<programme start="20150622080000 -0300" stop="20150622120000 -0300" channel="XTR" program_id="0000217661" event_id="000000100557779" series_key="">
<title lang="pt">Novidades na sua Locadora Virtual</title>
<desc>Assista na hora que quiser e quantas vezes desejar! Para utilizar a sua Locadora Virtual, basta acessar o botão "Menu" no seu controle remoto e utilizar as teclas de navegação para selecionar a categoria desejada.</desc>
<category lang="pt">Variedades</category>
<category lang="pt">Diversos</category>
<image>
<image_name position="1">0000217661.jpg</image_name>
<image_broadcast>0000217661</image_broadcast>
<image_copyright>Image supplied by Broadcasters</image_copyright>
</image>
<video>
<colour>yes</colour>
</video>
<rating system="Advisory">
<value>Programa livre para todas as idades</value>
</rating>
</programme>
<programme start="20150622120000 -0300" stop="20150622160000 -0300" channel="XTR" program_id="0000217661" event_id="000000100557780" series_key="">
<title lang="pt">Novidades na sua Locadora Virtual</title>
<desc>Assista na hora que quiser e quantas vezes desejar! Para utilizar a sua Locadora Virtual, basta acessar o botão "Menu" no seu controle remoto e utilizar as teclas de navegação para selecionar a categoria desejada.</desc>
<category lang="pt">Variedades</category>
<category lang="pt">Diversos</category>
<image>
<image_name position="1">0000217661.jpg</image_name>
<image_broadcast>0000217661</image_broadcast>
<image_copyright>Image supplied by Broadcasters</image_copyright>
</image>
<video>
<colour>yes</colour>
</video>
<rating system="Advisory">
<value>Programa livre para todas as idades</value>
</rating>
</programme>
<programme start="20150622160000 -0300" stop="20150622200000 -0300" channel="XTR" program_id="0000217661" event_id="000000100557781" series_key="">
<title lang="pt">Novidades na sua Locadora Virtual</title>
<desc>Assista na hora que quiser e quantas vezes desejar! Para utilizar a sua Locadora Virtual, basta acessar o botão "Menu" no seu controle remoto e utilizar as teclas de navegação para selecionar a categoria desejada.</desc>
<category lang="pt">Variedades</category>
<category lang="pt">Diversos</category>
<image>
<image_name position="1">0000217661.jpg</image_name>
<image_broadcast>0000217661</image_broadcast>
<image_copyright>Image supplied by Broadcasters</image_copyright>
</image>
<video>
<colour>yes</colour>
</video>
<rating system="Advisory">
<value>Programa livre para todas as idades</value>
</rating>
</programme>
<programme start="20150622200000 -0300" stop="20150623000000 -0300" channel="XTR" program_id="0000217661" event_id="000000100557782" series_key="">
<title lang="pt">Novidades na sua Locadora Virtual</title>
<desc>Assista na hora que quiser e quantas vezes desejar! Para utilizar a sua Locadora Virtual, basta acessar o botão "Menu" no seu controle remoto e utilizar as teclas de navegação para selecionar a categoria desejada.</desc>
<category lang="pt">Variedades</category>
<category lang="pt">Diversos</category>
<image>
<image_name position="1">0000217661.jpg</image_name>
<image_broadcast>0000217661</image_broadcast>
<image_copyright>Image supplied by Broadcasters</image_copyright>
</image>
<video>
<colour>yes</colour>
</video>
<rating system="Advisory">
<value>Programa livre para todas as idades</value>
</rating>
</programme>
<programme start="20150623000000 -0300" stop="20150623040000 -0300" channel="XTR" program_id="0000217661" event_id="000000100557783" series_key="">
<title lang="pt">Novidades na sua Locadora Virtual</title>
<desc>Assista na hora que quiser e quantas vezes desejar! Para utilizar a sua Locadora Virtual, basta acessar o botão "Menu" no seu controle remoto e utilizar as teclas de navegação para selecionar a categoria desejada.</desc>
<category lang="pt">Variedades</category>
<category lang="pt">Diversos</category>
<image>
<image_name position="1">0000217661.jpg</image_name>
<image_broadcast>0000217661</image_broadcast>
<image_copyright>Image supplied by Broadcasters</image_copyright>
</image>
<video>
<colour>yes</colour>
</video>
<rating system="Advisory">
<value>Programa livre para todas as idades</value>
</rating>
</programme>
<programme start="20150623040000 -0300" stop="20150623080000 -0300" channel="XTR" program_id="0000217661" event_id="000000100557784" series_key="">
<title lang="pt">Novidades na sua Locadora Virtual</title>
<desc>Assista na hora que quiser e quantas vezes desejar! Para utilizar a sua Locadora Virtual, basta acessar o botão "Menu" no seu controle remoto e utilizar as teclas de navegação para selecionar a categoria desejada.</desc>
<category lang="pt">Variedades</category>
<category lang="pt">Diversos</category>
<image>
<image_name position="1">0000217661.jpg</image_name>
<image_broadcast>0000217661</image_broadcast>
<image_copyright>Image supplied by Broadcasters</image_copyright>
</image>
<video>
<colour>yes</colour>
</video>
<rating system="Advisory">
<value>Programa livre para todas as idades</value>
</rating>
</programme>
<programme start="20150623080000 -0300" stop="20150623120000 -0300" channel="XTR" program_id="0000217661" event_id="000000100557785" series_key="">
<title lang="pt">Novidades na sua Locadora Virtual</title>
<desc>Assista na hora que quiser e quantas vezes desejar! Para utilizar a sua Locadora Virtual, basta acessar o botão "Menu" no seu controle remoto e utilizar as teclas de navegação para selecionar a categoria desejada.</desc>
<category lang="pt">Variedades</category>
<category lang="pt">Diversos</category>
<image>
<image_name position="1">0000217661.jpg</image_name>
<image_broadcast>0000217661</image_broadcast>
<image_copyright>Image supplied by Broadcasters</image_copyright>
</image>
<video>
<colour>yes</colour>
</video>
<rating system="Advisory">
<value>Programa livre para todas as idades</value>
</rating>
</programme>
<programme start="20150623120000 -0300" stop="20150623160000 -0300" channel="XTR" program_id="0000217661" event_id="000000100557786" series_key="">
<title lang="pt">Novidades na sua Locadora Virtual</title>
<desc>Assista na hora que quiser e quantas vezes desejar! Para utilizar a sua Locadora Virtual, basta acessar o botão "Menu" no seu controle remoto e utilizar as teclas de navegação para selecionar a categoria desejada.</desc>
<category lang="pt">Variedades</category>
<category lang="pt">Diversos</category>
<image>
<image_name position="1">0000217661.jpg</image_name>
<image_broadcast>0000217661</image_broadcast>
<image_copyright>Image supplied by Broadcasters</image_copyright>
</image>
<video>
<colour>yes</colour>
</video>
<rating system="Advisory">
<value>Programa livre para todas as idades</value>
</rating>
</programme>
<programme start="20150623160000 -0300" stop="20150623200000 -0300" channel="XTR" program_id="0000217661" event_id="000000100557787" series_key="">
<title lang="pt">Novidades na sua Locadora Virtual</title>
<desc>Assista na hora que quiser e quantas vezes desejar! Para utilizar a sua Locadora Virtual, basta acessar o botão "Menu" no seu controle remoto e utilizar as teclas de navegação para selecionar a categoria desejada.</desc>
<category lang="pt">Variedades</category>
<category lang="pt">Diversos</category>
<image>
<image_name position="1">0000217661.jpg</image_name>
<image_broadcast>0000217661</image_broadcast>
<image_copyright>Image supplied by Broadcasters</image_copyright>
</image>
<video>
<colour>yes</colour>
</video>
<rating system="Advisory">
<value>Programa livre para todas as idades</value>
</rating>
</programme>
<programme start="20150623200000 -0300" stop="20150624000000 -0300" channel="XTR" program_id="0000217661" event_id="000000100557788" series_key="">
<title lang="pt">Novidades na sua Locadora Virtual</title>
<desc>Assista na hora que quiser e quantas vezes desejar! Para utilizar a sua Locadora Virtual, basta acessar o botão "Menu" no seu controle remoto e utilizar as teclas de navegação para selecionar a categoria desejada.</desc>
<category lang="pt">Variedades</category>
<category lang="pt">Diversos</category>
<image>
<image_name position="1">0000217661.jpg</image_name>
<image_broadcast>0000217661</image_broadcast>
<image_copyright>Image supplied by Broadcasters</image_copyright>
</image>
<video>
<colour>yes</colour>
</video>
<rating system="Advisory">
<value>Programa livre para todas as idades</value>
</rating>
</programme>
</tv>
